{
  "project_info": {
    "project_number": "1024423680478",
    "project_id": "car-rental-app-bec12",
    "storage_bucket": "car-rental-app-bec12.firebasestorage.app"
  },
  "client": [
    {
      "client_info": {
        "mobilesdk_app_id": "1:1024423680478:android:65c346378b88e3719a254f",
        "android_client_info": {
          "package_name": "com.example.car_rental"
        }
      },
      "oauth_client": [],
      "api_key": [
        {
          "current_key": "AIzaSyBq9WuB1LwN2LXgzNc_4hjPnREFEjBHYPc"
        }
      ],
      "services": {
        "appinvite_service": {
          "other_platform_oauth_client": []
        }
      }
    }
  ],
  "configuration_version": "1"
}